sdo/__init__.py
sdo/cli.py
sdo/cmd/__init__.py
sdo/cmd/cmd_data.py
sdo/cmd/cmd_events.py
sdo/cmd/cmd_goes.py
sdo/cmd/cmd_sood.py
sdo/cmd/data/__init__.py
sdo/cmd/data/cmd_download.py
sdo/cmd/data/cmd_patch.py
sdo/cmd/data/cmd_resize.py
sdo/cmd/events/__init__.py
sdo/cmd/events/cmd_analyze_events.py
sdo/cmd/events/cmd_list_events.py
sdo/cmd/events/cmd_load_events.py
sdo/cmd/goes/__init__.py
sdo/cmd/goes/cmd_download.py
sdo/cmd/goes/cmd_get.py
sdo/cmd/sood/__init__.py
sdo/cmd/sood/cmd_ae.py
sdo/cmd/sood/cmd_ce_vae.py
sdo/cmd/sood/cmd_threshold.py
sdo/cmd/sood/ae/__init__.py
sdo/cmd/sood/ae/cmd_predict.py
sdo/cmd/sood/ae/cmd_train.py
sdo/cmd/sood/ce_vae/__init__.py
sdo/cmd/sood/ce_vae/cmd_generate.py
sdo/cmd/sood/ce_vae/cmd_predict.py
sdo/cmd/sood/ce_vae/cmd_reconstruct.py
sdo/cmd/sood/ce_vae/cmd_train.py
sdo/cmd/sood/threshold/__init__.py
sdo/cmd/sood/threshold/cmd_predict.py
sdo/data_loader/__init__.py
sdo/data_loader/goes/__init__.py
sdo/data_loader/goes/cache.py
sdo/data_loader/image_param/__init__.py
sdo/data_loader/image_param/IP_CONSTANTS/CONSTANTS.py
sdo/data_loader/image_param/IP_CONSTANTS/URL_STRINGS.py
sdo/data_loader/image_param/IP_CONSTANTS/__init__.py
sdo/data_loader/image_param/api_wrappers/__init__.py
sdo/data_loader/image_param/api_wrappers/api_wrappers.py
sdo/data_loader/image_param/objects/__init__.py
sdo/data_loader/image_param/objects/spatiotemporal_event.py
sdo/data_loader/image_param/utils/__init__.py
sdo/data_loader/image_param/utils/coord_convertor.py
sdo/events/__init__.py
sdo/events/bboxes.py
sdo/events/event_loader.py
sdo/sood/__init__.py
sdo/sood/algorithms/__init__.py
sdo/sood/algorithms/ae_2d.py
sdo/sood/algorithms/ce_vae.py
sdo/sood/algorithms/threshold.py
sdo/sood/data/__init__.py
sdo/sood/data/chunk_sampler.py
sdo/sood/data/image_dataset.py
sdo/sood/data/path_dataset.py
sdo/sood/data/sdo_ml_v1_dataset.py
sdo/sood/data/sdo_ml_v2_dataset.py
sdo/sood/models/__init__.py
sdo/sood/models/aes.py
sdo/sood/models/iwgan_nets.py
sdo_cli-0.0.21.dist-info/LICENSE
sdo_cli-0.0.21.dist-info/METADATA
sdo_cli-0.0.21.dist-info/WHEEL
sdo_cli-0.0.21.dist-info/entry_points.txt
sdo_cli-0.0.21.dist-info/top_level.txt
sdo_cli-0.0.21.dist-info/RECORD
