Metadata-Version: 2.1
Name: sdo-cli
Version: 0.0.21
Summary: An ML practitioner's utility for working with SDO data.
Home-page: https://github.com/i4DS/sdo-cli
Author: Marius Giger
Author-email: marius.giger@fhnw.ch
License: UNKNOWN
Platform: UNKNOWN
Classifier: Programming Language :: Python :: 3
Classifier: License :: OSI Approved :: MIT License
Classifier: Operating System :: OS Independent
Requires-Python: >=3.8
License-File: LICENSE
Requires-Dist: beautifulsoup4 (>=4.11.1)
Requires-Dist: click (>=8.1.2)
Requires-Dist: dask (>=2022.5.0)
Requires-Dist: drms (>=0.6.2)
Requires-Dist: h5netcdf (>=1.0.0)
Requires-Dist: matplotlib (>=3.5.1)
Requires-Dist: munch (>=2.5.0)
Requires-Dist: opencv-python (>=4.5.5.64)
Requires-Dist: python-dotenv (>=0.20.0)
Requires-Dist: pandas (>=1.4.2)
Requires-Dist: pytorch-lightning (>=1.6.1)
Requires-Dist: scikit-learn (>=1.0.2)
Requires-Dist: Shapely (>=1.7.1)
Requires-Dist: SQLAlchemy (>=1.4.17)
Requires-Dist: sunpy (>=3.1.6)
Requires-Dist: torch (>=1.11.0)
Requires-Dist: tqdm (>=4.64.0)
Requires-Dist: torchmetrics (>=0.8.2)
Requires-Dist: torchvision (>=0.12.0)
Requires-Dist: wandb (>=0.12.15)
Requires-Dist: zeep (>=4.1.0)
Requires-Dist: zarr (>=2.11.3)
